setup.py
renv_device/__init__.py
renv_device.egg-info/PKG-INFO
renv_device.egg-info/SOURCES.txt
renv_device.egg-info/dependency_links.txt
renv_device.egg-info/requires.txt
renv_device.egg-info/top_level.txt
test/test_my_renv_device.py
test/test_renv_device.py