Metadata-Version: 1.1
Name: renv-device
Version: 0.1.0
Summary: Renv Device Programming library
Home-page: http://ogata-lab.jp/
Author: ysuga
Author-email: ysuga@ysuga.net
License: GPLv3
Download-URL: https://github.com/ogata-lab/python_renv_device
Platform: UNKNOWN
Classifier: Development Status :: 4 - Beta
Classifier: Environment :: Console
Classifier: Intended Audience :: Developers
Classifier: License :: OSI Approved :: GNU General Public License v3 (GPLv3)
Classifier: Natural Language :: English
Classifier: Operating System :: OS Independent
Classifier: Programming Language :: Python
Classifier: Topic :: Scientific/Engineering
